{
    "osm_id": 360838541,
    "name": "360838541",
    "centroid": {
        "lat": 10.7621246,
        "lon": 78.81981152
    },
    "polygon": [
        {
            "lat": 10.7621002,
            "lon": 78.8197627
        },
        {
            "lat": 10.7621569,
            "lon": 78.8197607
        },
        {
            "lat": 10.7621612,
            "lon": 78.8198847
        },
        {
            "lat": 10.7621045,
            "lon": 78.8198868
        },
        {
            "lat": 10.7621002,
            "lon": 78.8197627
        }
    ],
    "tags": {
        "building": "yes"
    }
}