{
    "osm_id": 484660911,
    "name": "Basketball court",
    "centroid": {
        "lat": 10.75711065,
        "lon": 78.8172061
    },
    "polygon": [
        {
            "lat": 10.7572189,
            "lon": 78.8170564
        },
        {
            "lat": 10.757242,
            "lon": 78.8174882
        },
        {
            "lat": 10.7569639,
            "lon": 78.8175049
        },
        {
            "lat": 10.7569409,
            "lon": 78.8170676
        },
        {
            "lat": 10.7570793,
            "lon": 78.8170631
        },
        {
            "lat": 10.7572189,
            "lon": 78.8170564
        }
    ],
    "tags": {
        "building": "yes",
        "name": "Basketball court"
    }
}