{
    "osm_id": 360860365,
    "name": "360860365",
    "centroid": {
        "lat": 10.7616356,
        "lon": 78.81974987999999
    },
    "polygon": [
        {
            "lat": 10.76167,
            "lon": 78.8196938
        },
        {
            "lat": 10.7616748,
            "lon": 78.8198308
        },
        {
            "lat": 10.761584,
            "lon": 78.819834
        },
        {
            "lat": 10.7615792,
            "lon": 78.819697
        },
        {
            "lat": 10.76167,
            "lon": 78.8196938
        }
    ],
    "tags": {
        "building": "yes"
    }
}